django_tomselect/__init__.py
django_tomselect/_types.py
django_tomselect/app_settings.py
django_tomselect/autocompletes.py
django_tomselect/cache.py
django_tomselect/constants.py
django_tomselect/context_processors.py
django_tomselect/forms.py
django_tomselect/lazy_utils.py
django_tomselect/logging.py
django_tomselect/middleware.py
django_tomselect/models.py
django_tomselect/py.typed
django_tomselect/request.py
django_tomselect/utils.py
django_tomselect/widgets.py
django_tomselect/locale/de/LC_MESSAGES/django.mo
django_tomselect/locale/de/LC_MESSAGES/django.po
django_tomselect/locale/es/LC_MESSAGES/django.mo
django_tomselect/locale/es/LC_MESSAGES/django.po
django_tomselect/static/django_tomselect/css/django-tomselect.css
django_tomselect/static/django_tomselect/js/django-tomselect.js
django_tomselect/static/django_tomselect/js/django-tomselect.min.js
django_tomselect/static/django_tomselect/js/django-tomselect.min.js.map
django_tomselect/static/django_tomselect/vendor/tom-select/css/tom-select.bootstrap4.css
django_tomselect/static/django_tomselect/vendor/tom-select/css/tom-select.bootstrap4.css.map
django_tomselect/static/django_tomselect/vendor/tom-select/css/tom-select.bootstrap4.min.css
django_tomselect/static/django_tomselect/vendor/tom-select/css/tom-select.bootstrap4.min.css.map
django_tomselect/static/django_tomselect/vendor/tom-select/css/tom-select.bootstrap5.css
django_tomselect/static/django_tomselect/vendor/tom-select/css/tom-select.bootstrap5.css.map
django_tomselect/static/django_tomselect/vendor/tom-select/css/tom-select.bootstrap5.min.css
django_tomselect/static/django_tomselect/vendor/tom-select/css/tom-select.bootstrap5.min.css.map
django_tomselect/static/django_tomselect/vendor/tom-select/css/tom-select.default.css
django_tomselect/static/django_tomselect/vendor/tom-select/css/tom-select.default.css.map
django_tomselect/static/django_tomselect/vendor/tom-select/css/tom-select.default.min.css
django_tomselect-2026.1.3.dist-info/licenses/LICENSE
django_tomselect-2026.1.3.dist-info/METADATA
django_tomselect-2026.1.3.dist-info/WHEEL
django_tomselect-2026.1.3.dist-info/top_level.txt
django_tomselect-2026.1.3.dist-info/RECORD
