Metadata-Version: 2.4
Name: django-tomselect
Version: 2026.1.3
Summary: Django autocomplete widgets and views using Tom Select
Author-email: Jack Linke <jacklinke@gmail.com>
License-Expression: MIT
Project-URL: Source, https://github.com/OmenApps/django-tomselect
Project-URL: Documentation, https://django-tomselect.readthedocs.io/en/latest/
Project-URL: Issues, https://github.com/OmenApps/django-tomselect/issues
Project-URL: Changelog, https://github.com/OmenApps/django-tomselect/releases
Keywords: django,autocomplete,tomselect,widget,forms,views,select,multiselect
Classifier: Environment :: Web Environment
Classifier: Framework :: Django
Classifier: Framework :: Django :: 4.2
Classifier: Framework :: Django :: 5.1
Classifier: Framework :: Django :: 5.2
Classifier: Framework :: Django :: 6.0
Classifier: Development Status :: 5 - Production/Stable
Classifier: Intended Audience :: Developers
Classifier: Operating System :: OS Independent
Classifier: Programming Language :: Python
Classifier: Programming Language :: Python :: 3
Classifier: Programming Language :: Python :: 3.11
Classifier: Programming Language :: Python :: 3.12
Classifier: Programming Language :: Python :: 3.13
Classifier: Programming Language :: Python :: 3.14
Classifier: Topic :: Software Development :: User Interfaces
Classifier: Topic :: Software Development :: Widget Sets
Requires-Python: <4.0,>=3.11
License-File: LICENSE
Requires-Dist: django>=4.2.27
Provides-Extra: dev
Requires-Dist: bandit>=1.9.3; extra == "dev"
Requires-Dist: coverage[toml]>=7.8.2; extra == "dev"
Requires-Dist: darglint>=1.8.1; extra == "dev"
Requires-Dist: django-extensions>=4.1; extra == "dev"
Requires-Dist: django-htmx>=1.27.0; extra == "dev"
Requires-Dist: flake8-bugbear>=24.12.12; extra == "dev"
Requires-Dist: flake8-docstrings>=1.7.0; extra == "dev"
Requires-Dist: flake8-rst-docstrings>=0.3.1; extra == "dev"
Requires-Dist: flake8>=7.2.0; extra == "dev"
Requires-Dist: furo>=2024.8.6; extra == "dev"
Requires-Dist: linkify-it-py>=2.0.3; extra == "dev"
Requires-Dist: myst-parser>=4.0.1; extra == "dev"
Requires-Dist: nox>=2025.11.12; extra == "dev"
Requires-Dist: pep8-naming>=0.15.1; extra == "dev"
Requires-Dist: pre-commit-hooks>=6.0.0; extra == "dev"
Requires-Dist: pre-commit>=4.5.1; extra == "dev"
Requires-Dist: Pygments>=2.19.1; extra == "dev"
Requires-Dist: pytest-asyncio>=0.26.0; extra == "dev"
Requires-Dist: pytest-cov>=6.1.1; extra == "dev"
Requires-Dist: pytest-django>=4.11.1; extra == "dev"
Requires-Dist: pytest>=8.3.5; extra == "dev"
Requires-Dist: python-environ>=0.4.54; extra == "dev"
Requires-Dist: pyupgrade>=3.21.2; extra == "dev"
Requires-Dist: ruff>=0.14.13; extra == "dev"
Requires-Dist: pip-audit>=2.7.3; extra == "dev"
Requires-Dist: sphinx-autobuild>=2024.10.3; extra == "dev"
Requires-Dist: sphinx-click>=6.0.0; extra == "dev"
Requires-Dist: sphinx>=8.2.3; extra == "dev"
Requires-Dist: Werkzeug>=3.1.3; extra == "dev"
Requires-Dist: xdoctest[colors]>=1.3.0; extra == "dev"
Dynamic: license-file
